clippersaver/__init__.py
clippersaver/clipper.py
clippersaver/dbase/__init__.py
clippersaver/dbase/archiver7z.py
clippersaver_karjakak-0.4.3.dist-info/METADATA
clippersaver_karjakak-0.4.3.dist-info/WHEEL
clippersaver_karjakak-0.4.3.dist-info/entry_points.txt
clippersaver_karjakak-0.4.3.dist-info/top_level.txt
clippersaver_karjakak-0.4.3.dist-info/RECORD
