Metadata-Version: 2.1
Name: clippersaver-karjakak
Version: 0.4.3
Summary: ClipperSaver will clip everything copied and can be structured for env-var encryption use
Home-page: https://github.com/kakkarja/ClipperSaver
Author: karjakak
Author-email: kakkarja.github@gmail.com
License: BSD3 License
Platform: UNKNOWN
Classifier: Environment :: Win32 (MS Windows)
Classifier: Environment :: MacOS X
Classifier: Intended Audience :: End Users/Desktop
Classifier: Intended Audience :: Developers
Classifier: Programming Language :: Python :: 3.10
Classifier: License :: OSI Approved :: BSD License
Requires-Python: >=3.10
Requires-Dist: Clien-karjakak (>=0.1.7)
Requires-Dist: DecAn-karjakak (>=0.2.5)
Requires-Dist: envarclear-karjakak (>=0.1.0)
Requires-Dist: filepmon-karjakak (>=0.1.0)
Requires-Dist: filfla-karjakak (>=0.1.0)
Requires-Dist: filatt-karjakak (>=0.1.0)
Requires-Dist: py7zr (>=0.16.2)
Requires-Dist: excptr-karjakak (>=0.1.0)
